{
    "city":"Cleverland",
    "coordinates": [
        {
            "lat": 41.440796,
            "lng": -81.757305
         },
         {
            "lat": 41.418747,
            "lng": -81.854496
         },
         {
            "lat": 41.467775,
            "lng": -81.781998
         },
         {
            "lat": 41.494744,
            "lng": -81.717798
         },
         {
            "lat": 41.505733,
            "lng": -81.692354
         },
         {
            "lat": 41.513703,
            "lng": -81.597841
         }, 
         {
            "lat": 41.4543868,
            "lng": -81.7024839
         }, 
         {
            "lat": 41.4376627,
            "lng": -81.714879
         }, 
         {
            "lat": 41.470797,
            "lng": -81.7844987
         },   
         {
            "lat": 41.470797,
            "lng": -81.7844987
         }, 
         {
            "lat": 41.4920003,
            "lng": -81.6681905
         }, 

         {
            "lat": 41.4920003,
            "lng": -81.6681905
         },
         {
            "lat": 41.4920003,
            "lng": -81.6681905
         }




    ]
}